[
  {
    "id": "cf2183f7-5b5c-4f0c-bcc8-e81b88755682",
    "name": "Upstox",
    "description": "Upstox is a tech-first discount broking firm in India that provides trading services across different segments, including mutual funds, equities, commodities, futures, and options.",
    "slug": "UPSTOX",
    "url": "https://upstox.com/",
    "maintenance_mode": false,
    "allows_fractional_units": null,
    "allows_trading": false,
    "has_reporting": false,
    "is_real_time_connection": true,
    "aws_s3_logo_url": "https://passiv-brokerage-logos.s3.ca-central-1.amazonaws.com/upstox-logo.png",
    "aws_s3_square_logo_url": "https://passiv-brokerage-logos.s3.ca-central-1.amazonaws.com/upstox-logo-square.png",
    "open_url": "https://login.upstox.com/",
    "display_name": "Upstox",
    "enabled": true,
    "has_option_position_support": false,
    "has_option_activities_support": false,
    "has_option_trading_support": false,
    "allows_cryptocurrency_symbols": false,
    "allows_cryptocurrency_and_regular_securities": false
  },
  {
    "id": "0cbf540e-2ecf-4031-b1cd-663b5f124d6a",
    "name": "Trading212",
    "description": "Trading 212 is a fintech company that democratises the financial markets with free, smart and easy to use apps, enabling anyone to trade Stocks, ETFs, Forex, Commodities, and more.",
    "slug": "TRADING212",
    "url": "https://www.trading212.com/",
    "maintenance_mode": false,
    "allows_fractional_units": true,
    "allows_trading": false,
    "has_reporting": false,
    "is_real_time_connection": true,
    "aws_s3_logo_url": "https://passiv-brokerage-logos.s3.ca-central-1.amazonaws.com/trading212-logo.png",
    "aws_s3_square_logo_url": "https://passiv-brokerage-logos.s3.ca-central-1.amazonaws.com/trading212-logo-square.png",
    "open_url": "https://www.trading212.com/",
    "display_name": "Trading212",
    "enabled": true,
    "has_option_position_support": false,
    "has_option_activities_support": false,
    "has_option_trading_support": false,
    "allows_cryptocurrency_symbols": false,
    "allows_cryptocurrency_and_regular_securities": false
  },
  {
    "id": "b4f1112b-20e5-4d93-a284-ea0d098a2ddc",
    "name": "Commsec",
    "description": "CommSec is the first choice when considering retail online trading partners.",
    "slug": "COMMSEC",
    "url": "https://www.commsec.com/au",
    "maintenance_mode": false,
    "allows_fractional_units": null,
    "allows_trading": false,
    "has_reporting": true,
    "is_real_time_connection": true,
    "aws_s3_logo_url": "https://passiv-brokerage-logos.s3.ca-central-1.amazonaws.com/commsec-logo.png",
    "aws_s3_square_logo_url": "https://passiv-brokerage-logos.s3.ca-central-1.amazonaws.com/commsec-logo-square.jpg",
    "open_url": "https://www.commsec.com.au/accounts/share-trading.html?icid=public:loginpage:newtocommsec_joinnow",
    "display_name": "CommSec",
    "enabled": true,
    "has_option_position_support": false,
    "has_option_activities_support": false,
    "has_option_trading_support": false,
    "allows_cryptocurrency_symbols": false,
    "allows_cryptocurrency_and_regular_securities": false
  },
  {
    "id": "aac2a0a9-88d8-48ce-9916-182bd76b56ad",
    "name": "Bux",
    "description": "",
    "slug": "BUX",
    "url": "https://getbux.com/",
    "maintenance_mode": false,
    "allows_fractional_units": null,
    "allows_trading": false,
    "has_reporting": true,
    "is_real_time_connection": true,
    "aws_s3_logo_url": "https://passiv-brokerage-logos.s3.ca-central-1.amazonaws.com/bux-logo.png",
    "aws_s3_square_logo_url": "https://passiv-brokerage-logos.s3.ca-central-1.amazonaws.com/bux-square-logo.jpg",
    "open_url": "",
    "display_name": "Bux",
    "enabled": true,
    "has_option_position_support": false,
    "has_option_activities_support": false,
    "has_option_trading_support": false,
    "allows_cryptocurrency_symbols": false,
    "allows_cryptocurrency_and_regular_securities": false
  },
  {
    "id": "cdea2b1d-ff2c-4d19-9f2f-88031d5d8e47",
    "name": "Stake",
    "description": "Stake breaks barriers to give you direct access to the world’s biggest market.",
    "slug": "STAKE",
    "url": "https://hellostake.com/uk",
    "maintenance_mode": false,
    "allows_fractional_units": true,
    "allows_trading": true,
    "has_reporting": true,
    "is_real_time_connection": true,
    "aws_s3_logo_url": "https://passiv-brokerage-logos.s3.ca-central-1.amazonaws.com/stake-uk-logo.png",
    "aws_s3_square_logo_url": "https://passiv-brokerage-logos.s3.ca-central-1.amazonaws.com/stake-logo-square.png",
    "open_url": "https://trading.hellostake.com/sign-up",
    "display_name": "Stake UK",
    "enabled": true,
    "has_option_position_support": null,
    "has_option_activities_support": null,
    "has_option_trading_support": null,
    "allows_cryptocurrency_symbols": false,
    "allows_cryptocurrency_and_regular_securities": false
  },
  {
    "id": "b2ab13d8-da9f-48c0-8fb1-48331ba5deeb",
    "name": "Fidelity",
    "description": "Fidelity is an American multinational financial services corporation based in Boston, Massachusetts.",
    "slug": "FIDELITY",
    "url": "https://www.fidelity.com/",
    "maintenance_mode": false,
    "allows_fractional_units": true,
    "allows_trading": false,
    "has_reporting": true,
    "is_real_time_connection": true,
    "aws_s3_logo_url": "https://passiv-brokerage-logos.s3.ca-central-1.amazonaws.com/fidelity-logo.png",
    "aws_s3_square_logo_url": "https://passiv-brokerage-logos.s3.ca-central-1.amazonaws.com/fidelity-logo-square.png",
    "open_url": "https://fidelity.com",
    "display_name": "Fidelity",
    "enabled": true,
    "has_option_position_support": true,
    "has_option_activities_support": true,
    "has_option_trading_support": false,
    "allows_cryptocurrency_symbols": false,
    "allows_cryptocurrency_and_regular_securities": false
  },
  {
    "id": "905872ac-a7b1-4031-a31f-790cba1bfc94",
    "name": "Wealthsimple Trade",
    "description": "Wealthsimple Trade is a Canadian brokerage that allows you to buy and sell stocks and ETFs with no trading commissions.",
    "slug": "WEALTHSIMPLETRADE",
    "url": "https://www.wealthsimple.com/en-ca/product/trade/",
    "maintenance_mode": false,
    "allows_fractional_units": true,
    "allows_trading": true,
    "has_reporting": true,
    "is_real_time_connection": true,
    "aws_s3_logo_url": "https://passiv-brokerage-logos.s3.ca-central-1.amazonaws.com/wealthsimple-logo.png",
    "aws_s3_square_logo_url": "https://passiv-brokerage-logos.s3.ca-central-1.amazonaws.com/wealthsimple-trade-logo-square.png",
    "open_url": "https://www.wealthsimple.com/en-ca/product/trade",
    "display_name": "Wealthsimple Trade",
    "enabled": true,
    "has_option_position_support": null,
    "has_option_activities_support": null,
    "has_option_trading_support": null,
    "allows_cryptocurrency_symbols": true,
    "allows_cryptocurrency_and_regular_securities": true
  },
  {
    "id": "c9f13f36-44d9-4c0a-8d0e-798f7dd587c0",
    "name": "TradeStation Simulated Trading",
    "description": "Simulated trading for stocks, ETFs, futures, options, or crypto with reliable execution on powerful platforms, broad market access, and competitive pricing models.",
    "slug": "TRADESTATION-SIM",
    "url": "https://www.tradestation.com/",
    "maintenance_mode": false,
    "allows_fractional_units": null,
    "allows_trading": true,
    "has_reporting": null,
    "is_real_time_connection": true,
    "aws_s3_logo_url": "https://passiv-brokerage-logos.s3.ca-central-1.amazonaws.com/tradestation-sim-logo.png",
    "aws_s3_square_logo_url": "https://passiv-brokerage-logos.s3.ca-central-1.amazonaws.com/tradestation-logo-square.png",
    "open_url": "https://getstarted2.tradestation.com/registration",
    "display_name": "TradeStation Sim",
    "enabled": true,
    "has_option_position_support": true,
    "has_option_activities_support": null,
    "has_option_trading_support": false,
    "allows_cryptocurrency_symbols": false,
    "allows_cryptocurrency_and_regular_securities": false
  },
  {
    "id": "76e6660e-09ce-4197-a1a0-c14bf5f20f69",
    "name": "Questrade",
    "description": "Rated as Canada's best online brokerage by MoneySense in 2019, Questrade is a great choice for Canadians to manage their wealth. Questrade has low fees, excellent customer support, and will even cover your account transfer costs up to $150.",
    "slug": "QUESTRADE-UNOFFICIAL",
    "url": "https://www.questrade.com/",
    "maintenance_mode": false,
    "allows_fractional_units": null,
    "allows_trading": true,
    "has_reporting": true,
    "is_real_time_connection": true,
    "aws_s3_logo_url": "https://passiv-brokerage-logos.s3.ca-central-1.amazonaws.com/questrade-logo.png",
    "aws_s3_square_logo_url": "https://passiv-brokerage-logos.s3.ca-central-1.amazonaws.com/questrade-logo-square.png",
    "open_url": "https://www.questrade.com/account-selection?oaa_promo=passiv",
    "display_name": "Questrade",
    "enabled": true,
    "has_option_position_support": true,
    "has_option_activities_support": true,
    "has_option_trading_support": false,
    "allows_cryptocurrency_symbols": false,
    "allows_cryptocurrency_and_regular_securities": false
  },
  {
    "id": "575a7887-1b34-4ec8-bd10-f78fd4e711c3",
    "name": "Coinbase",
    "description": "Coinbase is a secure online platform for buying, selling, transferring, and storing cryptocurrency.",
    "slug": "COINBASE",
    "url": "https://www.coinbase.com/",
    "maintenance_mode": false,
    "allows_fractional_units": true,
    "allows_trading": false,
    "has_reporting": true,
    "is_real_time_connection": true,
    "aws_s3_logo_url": "https://passiv-brokerage-logos.s3.ca-central-1.amazonaws.com/coinbase_logo.png",
    "aws_s3_square_logo_url": "https://passiv-brokerage-logos.s3.ca-central-1.amazonaws.com/coinbase-logo-square.jpg",
    "open_url": "https://www.coinbase.com/",
    "display_name": "Coinbase",
    "enabled": true,
    "has_option_position_support": null,
    "has_option_activities_support": null,
    "has_option_trading_support": null,
    "allows_cryptocurrency_symbols": true,
    "allows_cryptocurrency_and_regular_securities": false
  },
  {
    "id": "09b739ea-52f5-4eaa-a84d-b3149dfd3b25",
    "name": "Unocoin",
    "description": "Unocoin is India's most trusted place to trade Bitcoin (BTC), Ether (ETH) and Tether (USDT) and the largest ecosystem of traders in the country.",
    "slug": "UNOCOIN",
    "url": "https://www.unocoin.com/",
    "maintenance_mode": false,
    "allows_fractional_units": true,
    "allows_trading": true,
    "has_reporting": false,
    "is_real_time_connection": true,
    "aws_s3_logo_url": "https://passiv-brokerage-logos.s3.ca-central-1.amazonaws.com/unocoin-logo.png",
    "aws_s3_square_logo_url": "https://passiv-brokerage-logos.s3.ca-central-1.amazonaws.com/unocoin-logo-square.jpg",
    "open_url": "https://www.unocoin.com/in",
    "display_name": "Unocoin",
    "enabled": true,
    "has_option_position_support": null,
    "has_option_activities_support": null,
    "has_option_trading_support": null,
    "allows_cryptocurrency_symbols": true,
    "allows_cryptocurrency_and_regular_securities": false
  },
  {
    "id": "02952334-1d52-436f-ba74-f3e9a98ea635",
    "name": "Webull",
    "description": "Webull Financial LLC offers an electronic trading platform, for the commission-free trading of stocks, exchange traded funds, options, margins, and cryptocurrencies.",
    "slug": "WEBULL",
    "url": "https://www.webull.com/",
    "maintenance_mode": false,
    "allows_fractional_units": true,
    "allows_trading": true,
    "has_reporting": true,
    "is_real_time_connection": true,
    "aws_s3_logo_url": "https://passiv-brokerage-logos.s3.ca-central-1.amazonaws.com/webull.png",
    "aws_s3_square_logo_url": "https://passiv-brokerage-logos.s3.ca-central-1.amazonaws.com/webull-logo-square.jpg",
    "open_url": "https://www.webull.com/",
    "display_name": "Webull US",
    "enabled": true,
    "has_option_position_support": true,
    "has_option_activities_support": true,
    "has_option_trading_support": false,
    "allows_cryptocurrency_symbols": false,
    "allows_cryptocurrency_and_regular_securities": false
  },
  {
    "id": "58fdf1c7-744a-429d-9075-53d0350f31db",
    "name": "Zerodha",
    "description": "Zerodha is the largest stock brokerage firm in India with more than 4 million clients.",
    "slug": "ZERODHA",
    "url": "https://zerodha.com/",
    "maintenance_mode": false,
    "allows_fractional_units": null,
    "allows_trading": true,
    "has_reporting": true,
    "is_real_time_connection": true,
    "aws_s3_logo_url": "https://passiv-brokerage-logos.s3.ca-central-1.amazonaws.com/zerodha-logo.png",
    "aws_s3_square_logo_url": "https://passiv-brokerage-logos.s3.ca-central-1.amazonaws.com/zerodha-logo-square.png",
    "open_url": "https://zerodha.com/open-account/",
    "display_name": "Zerodha",
    "enabled": true,
    "has_option_position_support": false,
    "has_option_activities_support": false,
    "has_option_trading_support": false,
    "allows_cryptocurrency_symbols": false,
    "allows_cryptocurrency_and_regular_securities": false
  },
  {
    "id": "48b1b10d-04d4-4663-9e0b-f2ecd38fd978",
    "name": "DEGIRO",
    "description": "DEGIRO is a European brokerage company, based in Amsterdam. It was founded in 2008 by a group of five former employees of Binck Bank to service the professional market.",
    "slug": "DEGIRO",
    "url": "https://www.degiro.com/",
    "maintenance_mode": false,
    "allows_fractional_units": null,
    "allows_trading": true,
    "has_reporting": true,
    "is_real_time_connection": true,
    "aws_s3_logo_url": "https://passiv-brokerage-logos.s3.ca-central-1.amazonaws.com/degiro-logo.png",
    "aws_s3_square_logo_url": "https://passiv-brokerage-logos.s3.ca-central-1.amazonaws.com/degiro-logo-square.png",
    "open_url": "https://www.degiro.ie/",
    "display_name": "DEGIRO",
    "enabled": true,
    "has_option_position_support": false,
    "has_option_activities_support": false,
    "has_option_trading_support": false,
    "allows_cryptocurrency_symbols": false,
    "allows_cryptocurrency_and_regular_securities": false
  },
  {
    "id": "2f081990-b40c-44a4-ab6e-f6ff4c125e39",
    "name": "Schwab",
    "description": "Schwab is an American multinational financial services corporation based in San Francisco, California.",
    "slug": "SCHWAB",
    "url": "https://www.schwab.com/",
    "maintenance_mode": false,
    "allows_fractional_units": true,
    "allows_trading": false,
    "has_reporting": true,
    "is_real_time_connection": true,
    "aws_s3_logo_url": "https://passiv-brokerage-logos.s3.ca-central-1.amazonaws.com/schwab-logo.png",
    "aws_s3_square_logo_url": "https://passiv-brokerage-logos.s3.ca-central-1.amazonaws.com/schwab-logo-square.png",
    "open_url": "https://schwab.com",
    "display_name": "Schwab",
    "enabled": true,
    "has_option_position_support": true,
    "has_option_activities_support": true,
    "has_option_trading_support": false,
    "allows_cryptocurrency_symbols": false,
    "allows_cryptocurrency_and_regular_securities": false
  },
  {
    "id": "82377296-f588-4b17-8d16-663adf33c21f",
    "name": "E-Trade",
    "description": "E-Trade Financial Corporation (stylized as E*TRADE) is a financial services company, which offers an electronic trading platform to trade financial assets including common stocks, preferred stocks, futures contracts, exchange-traded funds, options, mutual funds, and fixed income investments.",
    "slug": "ETRADE",
    "url": "https://www.us.etrade.com/",
    "maintenance_mode": false,
    "allows_fractional_units": false,
    "allows_trading": false,
    "has_reporting": true,
    "is_real_time_connection": true,
    "aws_s3_logo_url": "https://passiv-brokerage-logos.s3.ca-central-1.amazonaws.com/etrade-logo.png",
    "aws_s3_square_logo_url": "https://passiv-brokerage-logos.s3.ca-central-1.amazonaws.com/etrade-logo-square.jpg",
    "open_url": "https://us.etrade.com/home",
    "display_name": "E*Trade",
    "enabled": true,
    "has_option_position_support": false,
    "has_option_activities_support": false,
    "has_option_trading_support": false,
    "allows_cryptocurrency_symbols": false,
    "allows_cryptocurrency_and_regular_securities": false
  },
  {
    "id": "d13f1750-de66-497c-892a-01917504eb58",
    "name": "Vanguard",
    "description": "The Vanguard Group is an American investment firm with more than $7 trillion of assets under management.",
    "slug": "VANGUARD",
    "url": "https://investor.vanguard.com",
    "maintenance_mode": false,
    "allows_fractional_units": false,
    "allows_trading": false,
    "has_reporting": true,
    "is_real_time_connection": true,
    "aws_s3_logo_url": "https://passiv-brokerage-logos.s3.ca-central-1.amazonaws.com/vanguard-logo.png",
    "aws_s3_square_logo_url": "https://passiv-brokerage-logos.s3.ca-central-1.amazonaws.com/vanguard-square-logo.jpg",
    "open_url": "https://vanguard.com",
    "display_name": "Vanguard US",
    "enabled": true,
    "has_option_position_support": false,
    "has_option_activities_support": false,
    "has_option_trading_support": false,
    "allows_cryptocurrency_symbols": false,
    "allows_cryptocurrency_and_regular_securities": false
  },
  {
    "id": "af80a5d6-0b30-4fcd-888d-a907af373232",
    "name": "Tradier",
    "description": "Tradier is a REST-based, open, and secure API for investors, advisors, and traders.",
    "slug": "TRADIER",
    "url": "https://tradier.com/",
    "maintenance_mode": false,
    "allows_fractional_units": null,
    "allows_trading": true,
    "has_reporting": true,
    "is_real_time_connection": true,
    "aws_s3_logo_url": "https://passiv-brokerage-logos.s3.ca-central-1.amazonaws.com/tradier-logo.png",
    "aws_s3_square_logo_url": "https://passiv-brokerage-logos.s3.ca-central-1.amazonaws.com/tradier-logo-square.jpg",
    "open_url": "https://brokerage.tradier.com/signup?platform=109",
    "display_name": "Tradier",
    "enabled": true,
    "has_option_position_support": true,
    "has_option_activities_support": true,
    "has_option_trading_support": false,
    "allows_cryptocurrency_symbols": false,
    "allows_cryptocurrency_and_regular_securities": false
  },
  {
    "id": "9c5f3f2d-0a55-4bef-aa1c-77dfdd5fc2d4",
    "name": "Stake Australia",
    "description": "Stake breaks barriers to give you direct access to the world’s biggest market.",
    "slug": "STAKEAUS",
    "url": "https://hellostake.com/au",
    "maintenance_mode": false,
    "allows_fractional_units": true,
    "allows_trading": true,
    "has_reporting": true,
    "is_real_time_connection": true,
    "aws_s3_logo_url": "https://passiv-brokerage-logos.s3.ca-central-1.amazonaws.com/stake-aus-logo.png",
    "aws_s3_square_logo_url": "https://passiv-brokerage-logos.s3.ca-central-1.amazonaws.com/stake-logo-square.png",
    "open_url": "https://trading.hellostake.com/sign-up",
    "display_name": "Stake Australia",
    "enabled": true,
    "has_option_position_support": null,
    "has_option_activities_support": null,
    "has_option_trading_support": null,
    "allows_cryptocurrency_symbols": false,
    "allows_cryptocurrency_and_regular_securities": false
  },
  {
    "id": "ff3b5ae7-200e-4a87-8e14-6877979d4941",
    "name": "Alpaca Paper",
    "description": "Paper trading accounts for Alpaca.",
    "slug": "ALPACA-PAPER",
    "url": "https://alpaca.markets/",
    "maintenance_mode": false,
    "allows_fractional_units": true,
    "allows_trading": true,
    "has_reporting": true,
    "is_real_time_connection": true,
    "aws_s3_logo_url": "https://passiv-brokerage-logos.s3.ca-central-1.amazonaws.com/alpaca-paper-logo.png",
    "aws_s3_square_logo_url": "https://passiv-brokerage-logos.s3.ca-central-1.amazonaws.com/alpaca-logo-square.png",
    "open_url": "https://app.alpaca.markets/signup",
    "display_name": "Alpaca Paper",
    "enabled": true,
    "has_option_position_support": null,
    "has_option_activities_support": null,
    "has_option_trading_support": null,
    "allows_cryptocurrency_symbols": false,
    "allows_cryptocurrency_and_regular_securities": false
  },
  {
    "id": "ebf91a5b-0920-4266-9e36-f6cfe8c40946",
    "name": "Robinhood",
    "description": "Robinhood is an American multinational financial services corporation based in Menlo Park, California.",
    "slug": "ROBINHOOD",
    "url": "https://www.robinhood.com/",
    "maintenance_mode": false,
    "allows_fractional_units": true,
    "allows_trading": true,
    "has_reporting": true,
    "is_real_time_connection": true,
    "aws_s3_logo_url": "https://passiv-brokerage-logos.s3.ca-central-1.amazonaws.com/robinhood-logo.png",
    "aws_s3_square_logo_url": "https://passiv-brokerage-logos.s3.ca-central-1.amazonaws.com/robinhood-logo-square.png",
    "open_url": "https://robinhood.com",
    "display_name": "Robinhood",
    "enabled": true,
    "has_option_position_support": true,
    "has_option_activities_support": true,
    "has_option_trading_support": false,
    "allows_cryptocurrency_symbols": true,
    "allows_cryptocurrency_and_regular_securities": true
  },
  {
    "id": "797126b0-cb87-463c-8a96-4e73a9dfea26",
    "name": "Alpaca",
    "description": "Alpaca is a commission-free API-first brokerage servicing the USA and beyond.",
    "slug": "ALPACA",
    "url": "https://alpaca.markets/",
    "maintenance_mode": false,
    "allows_fractional_units": true,
    "allows_trading": true,
    "has_reporting": true,
    "is_real_time_connection": true,
    "aws_s3_logo_url": "https://passiv-brokerage-logos.s3.ca-central-1.amazonaws.com/alpaca-logo.png",
    "aws_s3_square_logo_url": "https://passiv-brokerage-logos.s3.ca-central-1.amazonaws.com/alpaca-logo-square.png",
    "open_url": "https://app.alpaca.markets/signup",
    "display_name": "Alpaca",
    "enabled": true,
    "has_option_position_support": null,
    "has_option_activities_support": null,
    "has_option_trading_support": null,
    "allows_cryptocurrency_symbols": false,
    "allows_cryptocurrency_and_regular_securities": false
  },
  {
    "id": "aab42dfa-2184-4259-972a-1119dea5903a",
    "name": "Binance",
    "description": "Binance Exchange is the largest crypto exchange by trade volume and one of the fastest crypto exchanges in the world.",
    "slug": "BINANCE",
    "url": "binance.com",
    "maintenance_mode": false,
    "allows_fractional_units": true,
    "allows_trading": false,
    "has_reporting": true,
    "is_real_time_connection": true,
    "aws_s3_logo_url": "https://passiv-brokerage-logos.s3.ca-central-1.amazonaws.com/binance-logo.png",
    "aws_s3_square_logo_url": "https://passiv-brokerage-logos.s3.ca-central-1.amazonaws.com/binance-logo-square.png",
    "open_url": "https://www.binance.com",
    "display_name": "Binance",
    "enabled": true,
    "has_option_position_support": null,
    "has_option_activities_support": null,
    "has_option_trading_support": null,
    "allows_cryptocurrency_symbols": true,
    "allows_cryptocurrency_and_regular_securities": false
  },
  {
    "id": "189e7950-9165-4147-83f7-b2135c150200",
    "name": "Kraken",
    "description": "Kraken is a US-based cryptocurrency exchange that allows users to trade more than 40 cryptocurrencies.",
    "slug": "KRAKEN",
    "url": "https://www.kraken.com/",
    "maintenance_mode": false,
    "allows_fractional_units": true,
    "allows_trading": true,
    "has_reporting": true,
    "is_real_time_connection": true,
    "aws_s3_logo_url": "https://passiv-brokerage-logos.s3.ca-central-1.amazonaws.com/kraken-logo.png",
    "aws_s3_square_logo_url": "https://passiv-brokerage-logos.s3.ca-central-1.amazonaws.com/kraken-logo-square.png",
    "open_url": "https://www.kraken.com/sign-up",
    "display_name": "Kraken",
    "enabled": false,
    "has_option_position_support": null,
    "has_option_activities_support": null,
    "has_option_trading_support": null,
    "allows_cryptocurrency_symbols": true,
    "allows_cryptocurrency_and_regular_securities": false
  },
  {
    "id": "fff73f8b-e411-40b8-ae84-60004e022051",
    "name": "TradeStation",
    "description": "Trade stocks, ETFs, futures, options, or crypto with reliable execution on powerful platforms, broad market access, and competitive pricing models.",
    "slug": "TRADESTATION",
    "url": "https://www.tradestation.com/",
    "maintenance_mode": false,
    "allows_fractional_units": null,
    "allows_trading": true,
    "has_reporting": null,
    "is_real_time_connection": true,
    "aws_s3_logo_url": "https://passiv-brokerage-logos.s3.ca-central-1.amazonaws.com/tradestation-logo.png",
    "aws_s3_square_logo_url": "https://passiv-brokerage-logos.s3.ca-central-1.amazonaws.com/tradestation-logo-square.png",
    "open_url": "https://getstarted2.tradestation.com/registration",
    "display_name": "TradeStation",
    "enabled": true,
    "has_option_position_support": true,
    "has_option_activities_support": null,
    "has_option_trading_support": false,
    "allows_cryptocurrency_symbols": false,
    "allows_cryptocurrency_and_regular_securities": false
  },
  {
    "id": "mt4-001",
    "name": "MetaTrader 4",
    "description": "MetaTrader 4 (MT4) is a popular trading platform, offering advanced charting, trading, and analysis features for forex and CFDs.",
    "slug": "mt4",
    "url": "https://www.metatrader4.com/",
    "maintenance_mode": false,
    "allows_fractional_units": false,
    "allows_trading": true,
    "has_reporting": true,
    "is_real_time_connection": true,
    "aws_s3_logo_url": "https://i.ibb.co/SwGm57x/mt4.png",
    "aws_s3_square_logo_url": "https://i.ibb.co/SwGm57x/mt4.png",
    "open_url": "https://www.metatrader4.com/en/trading-platform",
    "display_name": "MetaTrader 4",
    "enabled": false,
    "has_option_position_support": false,
    "has_option_activities_support": false,
    "has_option_trading_support": false,
    "allows_cryptocurrency_symbols": false,
    "allows_cryptocurrency_and_regular_securities": false
  },
  {
    "id": "mt5-001",
    "name": "MetaTrader 5",
    "description": "MetaTrader 5 (MT5) is an upgraded version of MT4, supporting more asset classes including forex, stocks, and futures, with more advanced trading features.",
    "slug": "mt5",
    "url": "https://www.metatrader5.com/",
    "maintenance_mode": false,
    "allows_fractional_units": false,
    "allows_trading": true,
    "has_reporting": true,
    "is_real_time_connection": true,
    "aws_s3_logo_url": "https://i.ibb.co/y8TvTTM/meta-5.png",
    "aws_s3_square_logo_url": "https://i.ibb.co/y8TvTTM/meta-5.png",
    "open_url": "https://www.metatrader5.com/en/trading-platform",
    "display_name": "MetaTrader 5",
    "enabled": false,
    "has_option_position_support": true,
    "has_option_activities_support": true,
    "has_option_trading_support": true,
    "allows_cryptocurrency_symbols": true,
    "allows_cryptocurrency_and_regular_securities": true
  }
]
